Workbook

Sheet Summary
A1: AfrimaPesa V1.0 — Development Plan Tracker
A2: Owner: Bruno Ganontha (CTO) · 16 weeks, 4 phases · Update the Status column on the Tasks and Exit Criteria sheets; everything here recalculates.
A4: Project start date (Monday of Week 1) | C4: 46293
A5: Planned launch (end of Week 16) | C5: =C4+7*15+4 -> 46402
A6: Today | C6: =TODAY() -> 46290
A7: Current project week | C7: =IF(C6<C4,"Not started",IF(C6>C5,"Past launch",INT((C6-C4)/7)+1)) -> Not started
A9: Phase | B9: Name | C9: Weeks | D9: Start | E9: End | F9: Tasks | G9: Done | H9: In progress | I9: Blocked | J9: % Tasks done | K9: Exit criteria | L9: Criteria met | M9: % Criteria met
A10: Phase 1 | B10: Infrastructure & Remittance Engine | C10: 1–4 | D10: =$C$4+7*0 -> 46293 | E10: =$C$4+7*3+4 -> 46318 | F10: =COUNTIFS(Tasks!$B:$B,"Phase 1") -> 13 | G10: =COUNTIFS(Tasks!$B:$B,"Phase 1",Tasks!$I:$I,"Done") -> 0 | H10: =COUNTIFS(Tasks!$B:$B,"Phase 1",Tasks!$I:$I,"In progress") -> 0 | I10: =COUNTIFS(Tasks!$B:$B,"Phase 1",Tasks!$I:$I,"Blocked") -> 0 | J10: =IF(F10=0,0,G10/F10) -> 0 | K10: =COUNTIFS('Exit Criteria'!$B:$B,"Phase 1") -> 5 | L10: =COUNTIFS('Exit Criteria'!$B:$B,"Phase 1",'Exit Criteria'!$E:$E,"Met") -> 0 | M10: =IF(K10=0,0,L10/K10) -> 0
A11: Phase 2 | B11: Commercial Banking & Admin | C11: 5–8 | D11: =$C$4+7*4 -> 46321 | E11: =$C$4+7*7+4 -> 46346 | F11: =COUNTIFS(Tasks!$B:$B,"Phase 2") -> 13 | G11: =COUNTIFS(Tasks!$B:$B,"Phase 2",Tasks!$I:$I,"Done") -> 0 | H11: =COUNTIFS(Tasks!$B:$B,"Phase 2",Tasks!$I:$I,"In progress") -> 0 | I11: =COUNTIFS(Tasks!$B:$B,"Phase 2",Tasks!$I:$I,"Blocked") -> 0 | J11: =IF(F11=0,0,G11/F11) -> 0 | K11: =COUNTIFS('Exit Criteria'!$B:$B,"Phase 2") -> 4 | L11: =COUNTIFS('Exit Criteria'!$B:$B,"Phase 2",'Exit Criteria'!$E:$E,"Met") -> 0 | M11: =IF(K11=0,0,L11/K11) -> 0
A12: Phase 3 | B12: Sovereign Yield Tracker | C12: 9–12 | D12: =$C$4+7*8 -> 46349 | E12: =$C$4+7*11+4 -> 46374 | F12: =COUNTIFS(Tasks!$B:$B,"Phase 3") -> 11 | G12: =COUNTIFS(Tasks!$B:$B,"Phase 3",Tasks!$I:$I,"Done") -> 0 | H12: =COUNTIFS(Tasks!$B:$B,"Phase 3",Tasks!$I:$I,"In progress") -> 0 | I12: =COUNTIFS(Tasks!$B:$B,"Phase 3",Tasks!$I:$I,"Blocked") -> 0 | J12: =IF(F12=0,0,G12/F12) -> 0 | K12: =COUNTIFS('Exit Criteria'!$B:$B,"Phase 3") -> 4 | L12: =COUNTIFS('Exit Criteria'!$B:$B,"Phase 3",'Exit Criteria'!$E:$E,"Met") -> 0 | M12: =IF(K12=0,0,L12/K12) -> 0
A13: Phase 4 | B13: Integration, Hardening & Launch | C13: 13–16 | D13: =$C$4+7*12 -> 46377 | E13: =$C$4+7*15+4 -> 46402 | F13: =COUNTIFS(Tasks!$B:$B,"Phase 4") -> 14 | G13: =COUNTIFS(Tasks!$B:$B,"Phase 4",Tasks!$I:$I,"Done") -> 0 | H13: =COUNTIFS(Tasks!$B:$B,"Phase 4",Tasks!$I:$I,"In progress") -> 0 | I13: =COUNTIFS(Tasks!$B:$B,"Phase 4",Tasks!$I:$I,"Blocked") -> 0 | J13: =IF(F13=0,0,G13/F13) -> 0 | K13: =COUNTIFS('Exit Criteria'!$B:$B,"Phase 4") -> 5 | L13: =COUNTIFS('Exit Criteria'!$B:$B,"Phase 4",'Exit Criteria'!$E:$E,"Met") -> 0 | M13: =IF(K13=0,0,L13/K13) -> 0
A14: Total | F14: =SUM(F10:F13) -> 51 | G14: =SUM(G10:G13) -> 0 | H14: =SUM(H10:H13) -> 0 | I14: =SUM(I10:I13) -> 0 | J14: =IF(F14=0,0,G14/F14) -> 0 | K14: =SUM(K10:K13) -> 18 | L14: =SUM(L10:L13) -> 0 | M14: =IF(K14=0,0,L14/K14) -> 0
A16: Open decisions & risks | C16: =COUNTIFS('Decisions & Risks'!$G:$G,"Open") -> 9
A18: Legend
A19: Yellow cell with blue text = input you can edit. Status columns use dropdowns. Rows turn green when Done/Met and red when Blocked.

Sheet Tasks
A1: ID | B1: Phase | C1: Week | D1: Workstream | E1: Task | F1: Deliverable / Demo | G1: Start | H1: End | I1: Status | J1: Owner | K1: Notes
A2: T01 | B2: Phase 1 | C2: 1 | D2: Infrastructure | E2: Set up monorepo (backend/, ingestion/, frontend/, infra/) and Docker Compose for local dev | F2: docker compose up starts full stack | G2: =Summary!$C$4+7*(C2-1) -> 46293 | H2: =G2+4 -> 46297 | I2: Not started | J2: Bruno
A3: T02 | B3: Phase 1 | C3: 1 | D3: Infrastructure | E3: Configure GitHub Actions CI: lint, type checks, tests | F3: CI green on main | G3: =Summary!$C$4+7*(C3-1) -> 46293 | H3: =G3+4 -> 46297 | I3: Not started | J3: Bruno
A4: T03 | B4: Phase 1 | C4: 1 | D4: Infrastructure | E4: Provision dev + staging environments, managed Postgres/TimescaleDB and Redis | F4: Staging reachable | G4: =Summary!$C$4+7*(C4-1) -> 46293 | H4: =G4+4 -> 46297 | I4: Not started | J4: Bruno
A5: T04 | B5: Phase 1 | C5: 2 | D5: Data model | E5: Create reference tables: countries, currencies, corridors (seed 18), providers, user preferences | F5: Migrations run cleanly | G5: =Summary!$C$4+7*(C5-1) -> 46300 | H5: =G5+4 -> 46304 | I5: Not started | J5: Bruno
A6: T05 | B6: Phase 1 | C6: 2 | D6: Data model | E6: Create hypertables fx_mid_rates and provider_quotes, plus ingestion_runs table | F6: Schema reviewed | G6: =Summary!$C$4+7*(C6-1) -> 46300 | H6: =G6+4 -> 46304 | I6: Not started | J6: Bruno
A7: T06 | B7: Phase 1 | C7: 2 | D7: Remittance | E7: Build calculation engine: F_transfer, A_net, effective rate, top-5 ranking by A_net | F7: Unit tests incl. fee edge cases | G7: =Summary!$C$4+7*(C7-1) -> 46300 | H7: =G7+4 -> 46304 | I7: Not started | J7: Bruno
A8: T07 | B8: Phase 1 | C8: 2 | D8: Remittance | E8: Start mid-market FX ingestion every 5 minutes for all 18 corridors | F8: Rates landing in DB | G8: =Summary!$C$4+7*(C8-1) -> 46300 | H8: =G8+4 -> 46304 | I8: Not started | J8: Bruno
A9: T08 | B9: Phase 1 | C9: 3 | D9: Ingestion | E9: Build base adapter interface (fetch → normalize → validate → store) with retries/backoff | F9: Framework merged | G9: =Summary!$C$4+7*(C9-1) -> 46307 | H9: =G9+4 -> 46311 | I9: Not started | J9: Bruno
A10: T09 | B10: Phase 1 | C10: 3 | D10: Ingestion | E10: Log every run to ingestion_runs; add sanity validator rejecting quotes far from mid-market | F10: Bad quotes rejected in tests | G10: =Summary!$C$4+7*(C10-1) -> 46307 | H10: =G10+4 -> 46311 | I10: Not started | J10: Bruno
A11: T10 | B11: Phase 1 | C11: 3 | D11: Remittance | E11: Build Wise adapter (public API) | F11: Wise quotes refresh on schedule | G11: =Summary!$C$4+7*(C11-1) -> 46307 | H11: =G11+4 -> 46311 | I11: Not started | J11: Bruno
A12: T11 | B12: Phase 1 | C12: 4 | D12: Remittance | E12: Build Remitly adapter (Playwright) | F12: Remitly quotes refresh on schedule | G12: =Summary!$C$4+7*(C12-1) -> 46314 | H12: =G12+4 -> 46318 | I12: Not started | J12: Bruno
A13: T12 | B13: Phase 1 | C13: 4 | D13: API | E13: Build GET /v1/remittance/compare endpoint; cache quotes per corridor in Redis | F13: p95 < 300 ms from cache | G13: =Summary!$C$4+7*(C13-1) -> 46314 | H13: =G13+4 -> 46318 | I13: Not started | J13: Bruno
... A52: T51 | B52: Phase 4 | C52: 16 | D52: Launch | E52: Soft launch | F52: V1.0 live | G52: =Summary!$C$4+7*(C52-1) -> 46398 | H52: =G52+4 -> 46402 | I52: Not started | J52: Bruno

Sheet Exit Criteria
A1: ID | B1: Phase | C1: Criterion | D1: Target / Test | E1: Status | F1: Evidence / Link | G1: Date verified
A2: E01 | B2: Phase 1 | C2: Mid-market FX refresh | D2: All 18 corridors refresh at least every 5 minutes | E2: Not met
A3: E02 | B3: Phase 1 | C3: Provider ingestion reliability | D3: Wise & Remitly: ≥95% successful runs over 3 days | E3: Not met
A4: E03 | B4: Phase 1 | C4: Compare API latency | D4: p95 < 300 ms served from cache | E4: Not met
A5: E04 | B5: Phase 1 | C5: Calculation engine tests | D5: ≥90% test coverage | E5: Not met
A6: E05 | B6: Phase 1 | C6: Stale data flagging | D6: Quotes older than 2× update interval flagged in API | E6: Not met
A7: E06 | B7: Phase 2 | C7: Bank coverage | D7: ≥80% of tracked banks show ≥1 deposit and ≥1 lending product | E7: Not met
A8: E07 | B8: Phase 2 | C8: Source transparency | D8: Every displayed rate shows source and last-verified date | E8: Not met
A9: E08 | B9: Phase 2 | C9: Audit log integrity | D9: Automated test proves audit rows cannot be modified | E9: Not met
A10: E09 | B10: Phase 2 | C10: Scraper monitoring | D10: Broken scraper shown within 1 run and alert fired | E10: Not met
A11: E10 | B11: Phase 3 | C11: Auction freshness | D11: Latest auction per country ingested within 24 h of publication | E11: Not met
A12: E11 | B12: Phase 3 | C12: Yield curves | D12: Curves generated when ≥4 tenor points; sparse curves labelled | E12: Not met
A13: E12 | B13: Phase 3 | C13: YTM accuracy | D13: YTM within 1 bp of reference examples | E13: Not met
... A19: E18 | B19: Phase 4 | C19: Rollback | D19: Rollback rehearsed at least once | E19: Not met

Sheet Decisions & Risks
A1: ID | B1: Type | C1: Item | D1: Impact on | E1: Needed by | F1: Owner | G1: Status | H1: Resolution / Notes
A2: D01 | B2: Decision | C2: Cloud provider (AWS recommended, since Phase 4 targets ECS) | D2: Infrastructure choices | E2: Before Week 1 | F2: Bruno + Claudio | G2: Open
A3: D02 | B3: Decision | C3: Mid-market FX data source (paid FX API) | D3: Remittance reference rate and ticker | E3: Before Week 1 | F3: Bruno + Claudio | G3: Open
A4: D03 | B4: Decision | C4: Legal position on scraping and reverse-engineered APIs | D4: Provider adapters | E4: Before Week 1 | F4: Claudio | G4: Open
A5: D04 | B5: Decision | C5: MVP cut line if schedule slips | D5: Launch date | E5: Before Week 1 | F5: Bruno + Claudio | G5: Open
A6: D05 | B6: Gap | C6: Pillar 4 (expert commentary), notifications and news feed not in roadmap; news needs Reuters/Bloomberg licensing | D6: Scope / launch date | E6: Before Week 1 | F6: Claudio | G6: Open
A7: D06 | B7: Risk | C7: Scraping / app API reverse engineering likely breaches provider ToS; fragile. Mitigate: UK legal advice, affiliate/partner programs | D7: Remittance module | E7: Before Phase 1 ends | F7: Claudio | G7: Open
A8: D07 | B8: Risk | C8: 'Real-time' sovereign data unrealistic: T-bills are weekly/biweekly auctions; live Eurobond prices need paid feed | D8: User expectations / budget | E8: Week 9 | F8: Bruno + Claudio | G8: Open
A9: D08 | B9: Risk | C9: Many banks publish no rates online (esp. lending) — needs ongoing manual collection by operations | D9: Banking coverage / staffing | E9: Week 5 | F9: Claudio | G9: Open
A10: D09 | B10: Risk | C10: 16 weeks tight for one developer covering ~40 data sources | D10: Launch date | E10: Ongoing | F10: Bruno | G10: Open
